indic_numtowords/__init__.py
indic_numtowords/numtowords.py
indic_numtowords/asm/__init__.py
indic_numtowords/asm/cardinal.py
indic_numtowords/asm/utils.py
indic_numtowords/asm/data/__init__.py
indic_numtowords/asm/data/nums.py
indic_numtowords/asm/data/user_variations.py
indic_numtowords/ben/__init__.py
indic_numtowords/ben/cardinal.py
indic_numtowords/ben/utils.py
indic_numtowords/ben/data/__init__.py
indic_numtowords/ben/data/nums.py
indic_numtowords/ben/data/user_variations.py
indic_numtowords/brx/__init__.py
indic_numtowords/brx/cardinal.py
indic_numtowords/brx/utils.py
indic_numtowords/brx/data/__init__.py
indic_numtowords/brx/data/nums.py
indic_numtowords/doi/__init__.py
indic_numtowords/doi/cardinal.py
indic_numtowords/doi/utils.py
indic_numtowords/doi/data/__init__.py
indic_numtowords/doi/data/nums.py
indic_numtowords/eng/__init__.py
indic_numtowords/eng/cardinal.py
indic_numtowords/eng/utils.py
indic_numtowords/eng/data/__init__.py
indic_numtowords/eng/data/nums.py
indic_numtowords/eng/data/user_variations.py
indic_numtowords/guj/__init__.py
indic_numtowords/guj/cardinal.py
indic_numtowords/guj/utils.py
indic_numtowords/guj/data/__init__.py
indic_numtowords/guj/data/nums.py
indic_numtowords/guj/data/user_variations.py
indic_numtowords/hin/__init__.py
indic_numtowords/hin/cardinal.py
indic_numtowords/hin/utils.py
indic_numtowords/hin/data/__init__.py
indic_numtowords/hin/data/nums.py
indic_numtowords/hin/data/user_variations.py
indic_numtowords/kan/__init__.py
indic_numtowords/kan/cardinal.py
indic_numtowords/kan/data/__init__.py
indic_numtowords/kan/data/nums.py
indic_numtowords/kan/data/user_variations.py
indic_numtowords/kas/__init__.py
indic_numtowords/kas/cardinal.py
indic_numtowords/kas/utils.py
indic_numtowords/kas/data/__init__.py
indic_numtowords/kas/data/nums.py
indic_numtowords/kok/__init__.py
indic_numtowords/kok/cardinal.py
indic_numtowords/kok/utils.py
indic_numtowords/kok/data/__init__.py
indic_numtowords/kok/data/nums.py
indic_numtowords-1.0.1.dist-info/licenses/LICENSE
indic_numtowords-1.0.1.dist-info/METADATA
indic_numtowords-1.0.1.dist-info/WHEEL
indic_numtowords-1.0.1.dist-info/top_level.txt
indic_numtowords-1.0.1.dist-info/RECORD
