Metadata-Version: 2.4
Name: indic_numtowords
Version: 1.0.1
Summary: A module to convert numbers to words for Indian languages and English.
Home-page: https://github.com/AI4Bharat/indic-numtowords
Author: AI4Bhārat
Author-email: opensource@ai4bharat.org
License: MIT
Project-URL: Source Code, https://github.com/AI4Bharat/indic-numtowords
Project-URL: Report Issues, https://github.com/AI4Bharat/indic-numtowords/issues
Classifier: Programming Language :: Python :: 3
Classifier: License :: OSI Approved :: MIT License
Classifier: Operating System :: OS Independent
Classifier: Topic :: Scientific/Engineering :: Artificial Intelligence
Classifier: Topic :: Software Development :: Libraries
Requires-Python: >=3.6
License-File: LICENSE
Dynamic: author
Dynamic: author-email
Dynamic: classifier
Dynamic: description
Dynamic: description-content-type
Dynamic: home-page
Dynamic: license
Dynamic: license-file
Dynamic: project-url
Dynamic: requires-python
Dynamic: summary
